LICENSE
MANIFEST.in
Makefile
README.md
requirements.txt
setup.py
docs/index.md
zeus_log_parser/__init__.py
zeus_log_parser/__version__.py
zeus_log_parser.egg-info/PKG-INFO
zeus_log_parser.egg-info/SOURCES.txt
zeus_log_parser.egg-info/dependency_links.txt
zeus_log_parser.egg-info/requires.txt
zeus_log_parser.egg-info/top_level.txt