Metadata-Version: 1.1
Name: zeus-log-parser
Version: 0.0.1
Summary: Log Parsing Tool for Zeus
Home-page: https://github.com/rajatguptarg/zeus-log-parser
Author: Rajat Gupta
Author-email: rajat.gupta712@gmail.com
License: ISC
Platform: UNKNOWN
Classifier: License :: OSI Approved :: MIT License
Classifier: Programming Language :: Python
Classifier: Programming Language :: Python :: 2.6
Classifier: Programming Language :: Python :: 2.7
Classifier: Programming Language :: Python :: 3
Classifier: Programming Language :: Python :: 3.3
Classifier: Programming Language :: Python :: 3.4
Classifier: Programming Language :: Python :: 3.5
Classifier: Programming Language :: Python :: 3.6
Classifier: Programming Language :: Python :: Implementation :: CPython
Classifier: Programming Language :: Python :: Implementation :: PyPy
